[
  {
    "id": "49657253",
    "title": "Development of fluoride ion conductors based on LaF3",
    "titleJa": "LaF3を基にしたフッ化物イオン伝導体の開発",
    "speakers": "Kazuaki Kawahara,Ryo Ishikawa,Shun Sasano,Naoya Shibata,Yuichi Ikuhara",
    "speakersJa": "川原一晃,石川亮,佐々野駿,柴田直哉,幾原雄一",
    "conference": "第64回電池討論会",
    "conferenceJa": "第64回電池討論会",
    "date": "2023-11-29",
    "year": "2023",
    "place": "",
    "placeJa": "",
    "isInvited": false
  },
  {
    "id": "43604844",
    "title": "Atomic-resolution STEM image denoising by total variation regularization",
    "titleJa": "Atomic-resolution STEM image denoising by total variation regularization",
    "speakers": "K. Kawahara,R. Ishikawa,S. Sasano,N. Shibata,Y. Ikuhara",
    "speakersJa": "K. Kawahara,R. Ishikawa,S. Sasano,N. Shibata,Y. Ikuhara",
    "conference": "IMC20",
    "conferenceJa": "IMC20",
    "date": "2023-09-12",
    "year": "2023",
    "place": "",
    "placeJa": "",
    "isInvited": false
  },
  {
    "id": "43604830",
    "title": "Atomic-Resolution STEM Image Denoising by Total Variation Regularization",
    "titleJa": "Atomic-Resolution STEM Image Denoising by Total Variation Regularization",
    "speakers": "K. Kawahara,R. Ishikawa,S. Sasano,N. Shibata,Y. Ikuhara",
    "speakersJa": "K. Kawahara,R. Ishikawa,S. Sasano,N. Shibata,Y. Ikuhara",
    "conference": "IAMNano2023",
    "conferenceJa": "IAMNano2023",
    "date": "2023-06-28",
    "year": "2023",
    "place": "",
    "placeJa": "",
    "isInvited": false
  },
  {
    "id": "43604822",
    "title": "全三階変動を用いた原子分解能STEM像のノイズ除去",
    "titleJa": "全三階変動を用いた原子分解能STEM像のノイズ除去",
    "speakers": "川原一晃,石川亮,佐々野駿,柴田直哉,幾原雄一",
    "speakersJa": "川原一晃,石川亮,佐々野駿,柴田直哉,幾原雄一",
    "conference": "日本顕微鏡学会第79回学術講演会",
    "conferenceJa": "日本顕微鏡学会第79回学術講演会",
    "date": "2023-06-26",
    "year": "2023",
    "place": "",
    "placeJa": "",
    "isInvited": false
  },
  {
    "id": "42409230",
    "title": "LaF3を基にしたフッ化物イオン伝導体の開発",
    "titleJa": "LaF3を基にしたフッ化物イオン伝導体の開発",
    "speakers": "川原一晃,石川亮,佐々野駿,柴田直哉,幾原雄一",
    "speakersJa": "川原一晃,石川亮,佐々野駿,柴田直哉,幾原雄一",
    "conference": "日本セラミックス協会2023年年会",
    "conferenceJa": "日本セラミックス協会2023年年会",
    "date": "2023-03",
    "year": "2023",
    "place": "",
    "placeJa": "",
    "isInvited": false
  }
]